[
    {
        "question": "Which JavaScript method converts a JSON string into an object?",
        "answers": [
        { "text": "JSON.parse()", "isCorrect": true },
        { "text": "JSON.stringify()", "isCorrect": false },
        { "text": "JSON.toObject()", "isCorrect": false },
        { "text": "JSON.convert()", "isCorrect": false }
        ]
    },
    {
        "question": "Which JavaScript method converts an object into a JSON string?",
        "answers": [
        { "text": "JSON.stringify()", "isCorrect": true },
        { "text": "JSON.parse()", "isCorrect": false },
        { "text": "JSON.toObject()", "isCorrect": false },
        { "text": "JSON.convert()", "isCorrect": false }
        ]
    }
]